./.gitignore
./CHANGELOG.md
./LICENSE.txt
./LICENSE_Pygments.txt
./README.md
./liquid2_lexer.py
./py.typed
./pyproject.toml
./.github/FUNDING.yml
./.github/workflows/lint.yaml
./.github/workflows/tests.yaml
./.github/workflows/typing.yaml
./tests/__init__.py
./tests/test_lex_block_comment.py
./tests/test_lex_raw_tag.py
./tests/test_liquid2_comment.py
./tests/examplefiles/example.liquid
./tests/examplefiles/example_liquid2.liquid
pygments_liquid2-0.2.0.dist-info/METADATA
pygments_liquid2-0.2.0.dist-info/WHEEL
pygments_liquid2-0.2.0.dist-info/entry_points.txt
pygments_liquid2-0.2.0.dist-info/licenses/LICENSE.txt
pygments_liquid2-0.2.0.dist-info/licenses/LICENSE_Pygments.txt
pygments_liquid2-0.2.0.dist-info/RECORD
