Metadata-Version: 2.4
Name: pygments-liquid2
Version: 0.2.0
Project-URL: Documentation, https://github.com/jg-rp/pygments-liquid2#readme
Project-URL: Issues, https://github.com/jg-rp/pygments-liquid2/issues
Project-URL: Source, https://github.com/jg-rp/pygments-liquid2
Author-email: James Prior <jamesgr.prior@gmail.com>
License: BSD-2-Clause
License-File: LICENSE.txt
License-File: LICENSE_Pygments.txt
Classifier: Development Status :: 4 - Beta
Classifier: License :: OSI Approved :: BSD License
Classifier: Programming Language :: Python
Classifier: Programming Language :: Python :: 3.8
Classifier: Programming Language :: Python :: 3.9
Classifier: Programming Language :: Python :: 3.10
Classifier: Programming Language :: Python :: 3.11
Classifier: Programming Language :: Python :: 3.12
Classifier: Programming Language :: Python :: 3.13
Classifier: Programming Language :: Python :: Implementation :: CPython
Classifier: Programming Language :: Python :: Implementation :: PyPy
Requires-Python: >=3.8
Requires-Dist: pygments>=2
